docs/conf.py
fabulous_paths/__init__.py
fabulous_paths/_installed_version.py
fabulous_paths/version.py
fabulous_paths/tests/__init__.py
fabulous_paths/tests/test_fabulous_paths.py
fabulous_paths/tests/test_data/generate_test_data.py
paths_cli_plugins/fabulous/__init__.py
paths_cli_plugins/fabulous/fabulous.py
fabulous_paths-0.0.1.dist-info/LICENSE
fabulous_paths-0.0.1.dist-info/METADATA
fabulous_paths-0.0.1.dist-info/WHEEL
fabulous_paths-0.0.1.dist-info/top_level.txt
fabulous_paths-0.0.1.dist-info/RECORD
