Metadata-Version: 2.1
Name: fabulous-paths
Version: 0.0.1
Summary: Tools for integrating OpenPathSampling and FABULOUS
Home-page: https://github.com/dwhswenson/fabulous-paths
Author: David W.H. Swenson and Ferry Hooft
Author-email: dwhs@hyperblazer.net
License: LGPL 3.0+
Platform: UNKNOWN
Classifier: Development Status :: 2 - Pre-Alpha
Classifier: Intended Audience :: Science/Research
Classifier: License :: OSI Approved :: GNU Lesser General Public License v3 or later (LGPLv3+)
Classifier: Operating System :: POSIX
Classifier: Programming Language :: Python :: 3
Classifier: Topic :: Scientific/Engineering :: Bio-Informatics
Classifier: Topic :: Scientific/Engineering :: Chemistry
Requires-Dist: openpathsampling-cli
